LICENSE
MANIFEST.in
README.md
setup.py
ofdlib2/__init__.py
ofdlib2/coefficients.h
ofdlib2/derivation.c
ofdlib2/fdtd.c
ofdlib2/filters.c
ofdlib2.egg-info/PKG-INFO
ofdlib2.egg-info/SOURCES.txt
ofdlib2.egg-info/dependency_links.txt
ofdlib2.egg-info/requires.txt
ofdlib2.egg-info/top_level.txt