Metadata-Version: 2.1
Name: ofdlib2
Version: 0.10.0
Summary: Finite difference tools
Home-page: UNKNOWN
Author: Cyril Desjouy
Author-email: cyril.desjouy@univ-lemans.fr
License: GPL
Platform: UNKNOWN
Classifier: Development Status :: 4 - Beta
Classifier: Programming Language :: Python :: 3
Classifier: Intended Audience :: Science/Research
Classifier: Topic :: Scientific/Engineering :: Physics
Classifier: Topic :: Software Development :: Libraries :: Python Modules
Classifier: License :: OSI Approved :: GNU General Public License v3 or later (GPLv3+)
License-File: LICENSE
